flexbase_client/__init__.py
flexbase_client/client.py
flexbase_client/exceptions.py
sphere_flexbase-0.1.0.dist-info/licenses/LICENSE
sphere_flexbase-0.1.0.dist-info/METADATA
sphere_flexbase-0.1.0.dist-info/WHEEL
sphere_flexbase-0.1.0.dist-info/top_level.txt
sphere_flexbase-0.1.0.dist-info/RECORD
