Metadata-Version: 2.4
Name: sphere-flexbase
Version: 0.1.0
Summary: Python client for FlexBase HTTP API
Home-page: https://github.com/sphere-team/sphere-flexbase
Author: Sphere Team
Author-email: Sphere Team <d.ushurov54@protonmail.com>
License-Expression: MIT
Project-URL: Homepage, https://github.com/dyde690/python-sphere-flexbase/
Project-URL: Bug Tracker, https://github.com/dyde690/python-sphere-flexbase/issues
Classifier: Development Status :: 4 - Beta
Classifier: Intended Audience :: Developers
Classifier: Operating System :: OS Independent
Classifier: Programming Language :: Python :: 3
Classifier: Programming Language :: Python :: 3.8
Classifier: Programming Language :: Python :: 3.9
Classifier: Programming Language :: Python :: 3.10
Classifier: Programming Language :: Python :: 3.11
Classifier: Topic :: Database
Classifier: Topic :: Software Development :: Libraries :: Python Modules
Requires-Python: >=3.8
License-File: LICENSE
Requires-Dist: requests>=2.31.0
Provides-Extra: dev
Requires-Dist: pytest>=7.0.0; extra == "dev"
Requires-Dist: pytest-cov>=4.0.0; extra == "dev"
Requires-Dist: black>=22.0.0; extra == "dev"
Requires-Dist: isort>=5.0.0; extra == "dev"
Requires-Dist: flake8>=4.0.0; extra == "dev"
Dynamic: author
Dynamic: home-page
Dynamic: license-file
Dynamic: requires-python
